imagekit/__init__.py
imagekit/admin.py
imagekit/conf.py
imagekit/exceptions.py
imagekit/files.py
imagekit/generatorlibrary.py
imagekit/hashers.py
imagekit/pkgmeta.py
imagekit/registry.py
imagekit/signals.py
imagekit/utils.py
imagekit/cachefiles/__init__.py
imagekit/cachefiles/backends.py
imagekit/cachefiles/namers.py
imagekit/cachefiles/strategies.py
imagekit/forms/__init__.py
imagekit/forms/fields.py
imagekit/management/__init__.py
imagekit/management/commands/__init__.py
imagekit/management/commands/generateimages.py
imagekit/models/__init__.py
imagekit/models/fields/__init__.py
imagekit/models/fields/files.py
imagekit/models/fields/utils.py
imagekit/processors/__init__.py
imagekit/processors/base.py
imagekit/processors/crop.py
imagekit/processors/resize.py
imagekit/processors/utils.py
imagekit/specs/__init__.py
imagekit/specs/sourcegroups.py
imagekit/templates/imagekit/admin/thumbnail.html
imagekit/templatetags/__init__.py
imagekit/templatetags/imagekit.py
django_imagekit-5.0.0.dist-info/AUTHORS
django_imagekit-5.0.0.dist-info/LICENSE
django_imagekit-5.0.0.dist-info/METADATA
django_imagekit-5.0.0.dist-info/WHEEL
django_imagekit-5.0.0.dist-info/pbr.json
django_imagekit-5.0.0.dist-info/top_level.txt
django_imagekit-5.0.0.dist-info/RECORD
