Metadata-Version: 2.1
Name: django-imagekit
Version: 5.0.0
Summary: Automated image processing for Django models.
Home-page: http://github.com/matthewwithanm/django-imagekit/
Author: Matthew Tretter
Author-email: m@tthewwithanm.com
Maintainer: Venelin Stoykov
Maintainer-email: venelin.stoykov@industria.tech
License: BSD
Classifier: Development Status :: 5 - Production/Stable
Classifier: Environment :: Web Environment
Classifier: Framework :: Django
Classifier: Intended Audience :: Developers
Classifier: License :: OSI Approved :: BSD License
Classifier: Operating System :: OS Independent
Classifier: Programming Language :: Python
Classifier: Programming Language :: Python :: 3
Classifier: Programming Language :: Python :: 3 :: Only
Classifier: Programming Language :: Python :: 3.6
Classifier: Programming Language :: Python :: 3.7
Classifier: Programming Language :: Python :: 3.8
Classifier: Programming Language :: Python :: 3.9
Classifier: Programming Language :: Python :: 3.10
Classifier: Programming Language :: Python :: 3.11
Classifier: Topic :: Utilities
License-File: LICENSE
License-File: AUTHORS
Requires-Dist: django-appconf
Requires-Dist: pilkit
Provides-Extra: async
Requires-Dist: django-celery>=3.0; extra == "async"
Provides-Extra: async-rq
Requires-Dist: django-rq>=0.6.0; extra == "async-rq"
Provides-Extra: async-dramatiq
Requires-Dist: django-dramatiq>=0.4.0; extra == "async-dramatiq"
